colorlog/__init__.py
colorlog/escape_codes.py
colorlog/formatter.py
colorlog/py.typed
colorlog/wrappers.py
colorlog-6.8.2.dist-info/LICENSE
colorlog-6.8.2.dist-info/METADATA
colorlog-6.8.2.dist-info/WHEEL
colorlog-6.8.2.dist-info/top_level.txt
colorlog-6.8.2.dist-info/RECORD
