Metadata-Version: 2.1
Name: colorlog
Version: 6.8.2
Summary: Add colours to the output of Python's logging module.
Home-page: https://github.com/borntyping/python-colorlog
Author: Sam Clements
Author-email: sam@borntyping.co.uk
License: MIT License
Classifier: Development Status :: 5 - Production/Stable
Classifier: Environment :: Console
Classifier: Intended Audience :: Developers
Classifier: License :: OSI Approved :: MIT License
Classifier: Operating System :: OS Independent
Classifier: Programming Language :: Python
Classifier: Programming Language :: Python :: 3
Classifier: Programming Language :: Python :: 3.6
Classifier: Programming Language :: Python :: 3.7
Classifier: Programming Language :: Python :: 3.8
Classifier: Programming Language :: Python :: 3.9
Classifier: Programming Language :: Python :: 3.10
Classifier: Topic :: Terminals
Classifier: Topic :: Utilities
Requires-Python: >=3.6
Provides-Extra: development
License-File: LICENSE
